{
  "id": "loi-n-15-278-1919-etablissant-une-carte-didentite-professionnelle-a-lusage-des-voyageurs-et-representants-de-commerce",
  "type": "statute",
  "title": "Loi n° 15-278-1919 établissant une carte d’identité professionnelle à l’usage des voyageurs et représentants de commerce.",
  "short_name": "Loi n° 15-278-1919 établissant une carte d’identité professionnelle à l’usage…",
  "status": "in_force",
  "reference": "15-278-1919",
  "issued_date": "1919-10-08",
  "url": "https://www.journalofficiel.dj/texte-juridique/loi-n-15-278-1919-etablissant-une-carte-didentite-professionnelle-a-lusage-des-voyageurs-et-representants-de-commerce/",
  "description": "établissant une carte d'identité professionnelle à l'usage des voyageurs et représentants de commerce.",
  "nature": "Loi",
  "institution": "ACTES DU POUVOIR CENTRAL",
  "visas": "",
  "signature": "<p style=\"margin: 0px;\">R. POINCAR&Eacute;</p>\n<p style=\"margin: 0px;\">Par le Pr&eacute;sident de la R&eacute;publique:</p>\n<p style=\"margin: 0px;\">Le Ministre du commerce, de l&rsquo;industrie,</p>\n<p style=\"margin: 0px;\">des postes et des t&eacute;l&eacute;graphes,</p>\n<p style=\"margin: 0px;\">&nbsp;</p>\n<p style=\"margin: 0px;\">CL&Eacute;NENTEL.</p>\n<p style=\"margin: 0px;\">Le garde des sceaux, Ministre de la justice,</p>\n<p style=\"margin: 0px;\">Louis NAIL.</p>\n<p style=\"margin: 0px;\">&nbsp;</p>\n<p style=\"margin: 0px;\">Le Ministre des finances,</p>\n<p style=\"margin: 0px;\">&nbsp;</p>\n<p style=\"margin: 0px;\">L.-L. KLOTZ.</p>\n<p style=\"margin: 0px;\">Le Ministre des affaires &eacute;trang&egrave;res,</p>\n<p style=\"margin: 0px;\">&nbsp;</p>\n<p style=\"margin: 0px;\">STEPREN PICHON.</p>\n<p style=\"margin: 0px;\">Le Ministre de l&rsquo;int&eacute;rieur,</p>\n<p style=\"margin: 0px;\">&nbsp;</p>\n<p style=\"margin: 0px;\">J. PAMS.</p>\n<p style=\"margin: 0px;\">Le Ministre des colonies,</p>\n<p style=\"margin: 0px;\">HENRY SIMON.</p>\n<p style=\"margin: 0px;\">&nbsp;</p>\n<p style=\"margin: 0px;\">&nbsp;</p>",
  "journal_issue_ids": [
    106086
  ],
  "provisions": [
    {
      "provision_ref": "body",
      "section": "body",
      "title": "Corps du texte",
      "content": "Art. 1er.— Toute personne exerçant, sur le territoire français, la profession de voyageur ou de représentant de commerce, est tenue de justifier de la possession d’une carte professionnelle d’identité établie dans les conditions prévues aux articles suivants.\n\n Art. 2.— La carte d’identité professionnelle sera signée du titulaire et indiquera son signalement descriptif, ses nom, prénoms, date et lieu de naissance, sa nationalité originaire et acquise s’il y a lieu, ainsi que son domicile. La carte portera, en outre, la photographie du titulaire oblitérée par le sceau de l’autorité qui l’aura délivrée. Toutes pièces d’état civil utiles devront être fournies à l’appui deses déclarations par le requérant. Ce dernier devra également produire l’attestation écrite des producteurs, industriels où commerçants qui l’emploient. Cette attestation sera visée par la chambre de commerce dans le ressort de laquelle se trouvera la maison représentée ou son principal établissement. La production de cette attestation sera mentionnée sur la carte professionnelle d’identité.\n\n Art. 3.— Si la maison représentée est située au colonies ou en pays de protectorat, les déclarations de l’établissement employeur devront être visées par les fonctionnaires désignés à cet effet par le gouverneur général, le gouverneur ou le résident supérieur.\n\n Art. 4.— Si la maison représentée est étrangère et n’a pas de succursale en France, les déclarations de l’établissement employeur devront être visées par l’agent consulaire français dans le ressort duquel se trouvera la maison étrangère où son principal établissement.\n\n Art. 5.— Les cartes d’identité professionnelle seront délivrées :\n\n En France, par l’autorité préfectorale du domicile du requérant ;\n\n Aux colonies et dans les pays de protectorat, par les fonctionnaires désignés à cet effet par le gouverneur général, le gouverneur ou le résident supérieur;\n\n A l’étranger, par l’agent consulaire dans le ressort duquel habite le voyageur ou le représentant de commerce.\n\n Art. 6.— La carte d’identité professionnelle devra être renouvelée tous les ans, dans les conditions fixées aux articles précédents.\n\n Toutes modifications apportées aux déclarations consignées à la carte d’identité professionnelle doivent être l’objet d’une déclaration faite au moment du renouvellement.\n\n La délivrance des cartes d’identité professionnelles donnera lieu à la perception d’un droit annuel de 40 fr. au profit de l’Etat.\n\n Art. 7.— Toute personne qui aura exercé la profession de voyageur ou de représentant de commerce sur le territoire français sans pouvoir justifier de Ja possession régulière de la carte d’identité professionnelle établie par la présente loi, ou qui sciemment aura fait des déclarations inexactes pour obtenir la délivrance de ladite carte, sera punie d’une amende de cinquante à deux cents francs (50 à 200 fr.) et, en cas de récidive, de deux cents à deux mille francs (200 à 2.000 fr.).\n\n Les mêmes pénalités seront applicables à toute personne convaincue d’avoir délivré des attestations ou certificats de complaisance.\n\n L’article 463 du code pénal est applicable aux infractions prévues par la présente loi.\n\n Art. 8.— Un délai de trois mois, à dater de la promulgation de la présente loi, est accordé à tous les voyageurs ou représentants de commerce exerçant leur profession sur le territoire Français pour se conformer aux dispositions qui précèdent.\n\n Art. 9.- La présente loi est applicable à l’Algérie, aux colonies et aux pays de protectorat.\n\n Art. 10.— Un décret fixera la forme et les dimensions de la carte d’identité professionnelle, ainsi que les détails d’application de la présente loi.\n\n La présente loi, délibérée et adoptée par le Sénat et la Chambre des députés, sera exécutée comme loi de l’Eat."
    },
    {
      "provision_ref": "signature",
      "section": "signature",
      "title": "Signature",
      "content": "<p style=\"margin: 0px;\">R. POINCAR&Eacute;</p>\n<p style=\"margin: 0px;\">Par le Pr&eacute;sident de la R&eacute;publique:</p>\n<p style=\"margin: 0px;\">Le Ministre du commerce, de l&rsquo;industrie,</p>\n<p style=\"margin: 0px;\">des postes et des t&eacute;l&eacute;graphes,</p>\n<p style=\"margin: 0px;\">&nbsp;</p>\n<p style=\"margin: 0px;\">CL&Eacute;NENTEL.</p>\n<p style=\"margin: 0px;\">Le garde des sceaux, Ministre de la justice,</p>\n<p style=\"margin: 0px;\">Louis NAIL.</p>\n<p style=\"margin: 0px;\">&nbsp;</p>\n<p style=\"margin: 0px;\">Le Ministre des finances,</p>\n<p style=\"margin: 0px;\">&nbsp;</p>\n<p style=\"margin: 0px;\">L.-L. KLOTZ.</p>\n<p style=\"margin: 0px;\">Le Ministre des affaires &eacute;trang&egrave;res,</p>\n<p style=\"margin: 0px;\">&nbsp;</p>\n<p style=\"margin: 0px;\">STEPREN PICHON.</p>\n<p style=\"margin: 0px;\">Le Ministre de l&rsquo;int&eacute;rieur,</p>\n<p style=\"margin: 0px;\">&nbsp;</p>\n<p style=\"margin: 0px;\">J. PAMS.</p>\n<p style=\"margin: 0px;\">Le Ministre des colonies,</p>\n<p style=\"margin: 0px;\">HENRY SIMON.</p>\n<p style=\"margin: 0px;\">&nbsp;</p>\n<p style=\"margin: 0px;\">&nbsp;</p>"
    }
  ]
}